{
  "meta": {
    "generatedAt": "2026-04-22T00:06:02.447565",
    "source": "clinical",
    "count": 24,
    "sources": [
      "https://m.saramin.co.kr/job-industry/job-list?cat_kewd=559&is_detail_search=y",
      "https://www.seoulmc.or.kr/site/recruit/recruitList.do",
      "https://ncc.recruiter.co.kr/app/jobnotice/list",
      "https://recruit.snubh.org/main/recruit/recruit_list.do"
    ],
    "errors": []
  },
  "jobs": [
    {
      "id": "clinical-1679586016624496746",
      "title": "[몸편한내과신경과]임상병리사 선생님 채용합니다. 몸편한내과신경과의원 대구 남구 경력2년↑ ~05.21(목)",
      "organization": "사람인",
      "category": "clinical",
      "track": "clinical",
      "region": "서울/경기",
      "employmentType": "임상병리",
      "postedAt": "",
      "deadline": "",
      "status": "unknown",
      "source": "사람인 임상병리",
      "sourceType": "job-board",
      "url": "https://m.saramin.co.kr/job-search/view?rec_idx=53683102&t_category=job_recruit&t_content=SRI_M_050_2LV-JOB_MIX_RCT_NONMEM&referNonce=4b6828e7475fd0cc4f41&",
      "description": "[몸편한내과신경과]임상병리사 선생님 채용합니다. 몸편한내과신경과의원 대구 남구 경력2년↑ ~05.21(목) 스크랩"
    },
    {
      "id": "clinical-3802769005419784482",
      "title": "[녹십자 그룹] GC셀 임상병리사 모집 (제주, 계약직) (주)지씨셀 제주 서귀포시 경력무관 채용시",
      "organization": "사람인",
      "category": "clinical",
      "track": "clinical",
      "region": "서울/경기",
      "employmentType": "임상병리",
      "postedAt": "",
      "deadline": "",
      "status": "unknown",
      "source": "사람인 임상병리",
      "sourceType": "job-board",
      "url": "https://m.saramin.co.kr/job-search/view?rec_idx=53674280&t_category=job_recruit&t_content=SRI_M_050_2LV-JOB_MIX_RCT_NONMEM&referNonce=4b6828e7475fd0cc4f41&",
      "description": "[녹십자 그룹] GC셀 임상병리사 모집 (제주, 계약직) (주)지씨셀 제주 서귀포시 경력무관 채용시 스크랩"
    },
    {
      "id": "clinical-7436875213600247322",
      "title": "임상병리사 정규직 모집 대구 수성구 경력1년↑ 초대졸↑ 강미정연합내과의원 기업이미지 ~05.17(일)",
      "organization": "사람인",
      "category": "clinical",
      "track": "clinical",
      "region": "서울/경기",
      "employmentType": "임상병리",
      "postedAt": "",
      "deadline": "",
      "status": "unknown",
      "source": "사람인 임상병리",
      "sourceType": "job-board",
      "url": "https://m.saramin.co.kr/job-search/view?rec_idx=53653453&cn=job-industry&cns=recently-list&t_category=job_recruit&t_content=generic&referNonce=",
      "description": "임상병리사 정규직 모집 대구 수성구 경력1년↑ 초대졸↑ 강미정연합내과의원 기업이미지 ~05.17(일) 스크랩 입사지원"
    },
    {
      "id": "clinical-6347366516500974295",
      "title": "[녹십자 그룹] GC셀 검체 관리 서비스 매니저 채용 (의정부) 경기 의정부시 외 평균근속 2~5년 (주)지씨셀 기업이미지 채용시",
      "organization": "사람인",
      "category": "clinical",
      "track": "clinical",
      "region": "경기",
      "employmentType": "임상병리",
      "postedAt": "",
      "deadline": "",
      "status": "unknown",
      "source": "사람인 임상병리",
      "sourceType": "job-board",
      "url": "https://m.saramin.co.kr/job-search/view?rec_idx=53619718&cn=job-industry&cns=recently-list&t_category=job_recruit&t_content=generic&referNonce=",
      "description": "[녹십자 그룹] GC셀 검체 관리 서비스 매니저 채용 (의정부) 경기 의정부시 외 평균근속 2~5년 (주)지씨셀 기업이미지 채용시 스크랩 입사지원"
    },
    {
      "id": "clinical-2789323602892019542",
      "title": "[몸편한내과신경과]임상병리사 선생님 채용합니다. 대구 남구 외 경력2년↑ 초대졸↑ 몸편한내과신경과의원 기업이미지 ~05.21(목)",
      "organization": "사람인",
      "category": "clinical",
      "track": "clinical",
      "region": "서울/경기",
      "employmentType": "임상병리",
      "postedAt": "",
      "deadline": "",
      "status": "unknown",
      "source": "사람인 임상병리",
      "sourceType": "job-board",
      "url": "https://m.saramin.co.kr/job-search/view?rec_idx=53683102&cn=job-industry&cns=recently-list&t_category=job_recruit&t_content=generic&referNonce=",
      "description": "[몸편한내과신경과]임상병리사 선생님 채용합니다. 대구 남구 외 경력2년↑ 초대졸↑ 몸편한내과신경과의원 기업이미지 ~05.21(목) 스크랩 입사지원"
    },
    {
      "id": "clinical-7061985022081846732",
      "title": "의료 조회 급상승 종합병원 특수검진 임상병리사 채용 경기 오산시 경력1년↑ 초대졸↑ 조은오산병원 기업이미지 ~04.30(목)",
      "organization": "사람인",
      "category": "clinical",
      "track": "clinical",
      "region": "경기",
      "employmentType": "임상병리",
      "postedAt": "",
      "deadline": "",
      "status": "unknown",
      "source": "사람인 임상병리",
      "sourceType": "job-board",
      "url": "https://m.saramin.co.kr/job-search/view?rec_idx=53288278&cn=job-industry&cns=recently-list&t_category=job_recruit&t_content=generic&referNonce=",
      "description": "의료 조회 급상승 종합병원 특수검진 임상병리사 채용 경기 오산시 경력1년↑ 초대졸↑ 조은오산병원 기업이미지 ~04.30(목) 스크랩 입사지원"
    },
    {
      "id": "clinical-8148229732755481243",
      "title": "[문산중앙병원] 임상병리사 모집합니다 [신입직] 경기 파주시 신입 초대졸↑ (의)강영의료재단 기업이미지 ~05.07(목)",
      "organization": "사람인",
      "category": "clinical",
      "track": "clinical",
      "region": "경기",
      "employmentType": "임상병리",
      "postedAt": "",
      "deadline": "",
      "status": "unknown",
      "source": "사람인 임상병리",
      "sourceType": "job-board",
      "url": "https://m.saramin.co.kr/job-search/view?rec_idx=53553748&cn=job-industry&cns=recently-list&t_category=job_recruit&t_content=generic&referNonce=",
      "description": "[문산중앙병원] 임상병리사 모집합니다 [신입직] 경기 파주시 신입 초대졸↑ (의)강영의료재단 기업이미지 ~05.07(목) 스크랩 입사지원"
    },
    {
      "id": "clinical-610705068679931689",
      "title": "[녹십자 그룹] GC셀 임상병리사 모집 (제주, 계약직) 제주 서귀포시 성과급 연 1회 (주)지씨셀 기업이미지 채용시",
      "organization": "사람인",
      "category": "clinical",
      "track": "clinical",
      "region": "서울/경기",
      "employmentType": "임상병리",
      "postedAt": "",
      "deadline": "",
      "status": "unknown",
      "source": "사람인 임상병리",
      "sourceType": "job-board",
      "url": "https://m.saramin.co.kr/job-search/view?rec_idx=53674280&cn=job-industry&cns=recently-list&t_category=job_recruit&t_content=generic&referNonce=",
      "description": "[녹십자 그룹] GC셀 임상병리사 모집 (제주, 계약직) 제주 서귀포시 성과급 연 1회 (주)지씨셀 기업이미지 채용시 스크랩 입사지원"
    },
    {
      "id": "clinical-296902659948139755",
      "title": "부천중앙병원 오전 아르바이트 임상병리사 구인 경기 부천시 경력 학력무관 부천중앙병원 기업이미지 ~05.20(수)",
      "organization": "사람인",
      "category": "clinical",
      "track": "clinical",
      "region": "경기",
      "employmentType": "임상병리",
      "postedAt": "",
      "deadline": "",
      "status": "unknown",
      "source": "사람인 임상병리",
      "sourceType": "job-board",
      "url": "https://m.saramin.co.kr/job-search/view?rec_idx=53669599&cn=job-industry&cns=recently-list&t_category=job_recruit&t_content=generic&referNonce=",
      "description": "부천중앙병원 오전 아르바이트 임상병리사 구인 경기 부천시 경력 학력무관 부천중앙병원 기업이미지 ~05.20(수) 스크랩 입사지원"
    },
    {
      "id": "clinical-7564052720856557511",
      "title": "임상병리사 구인 경남 창원시 의창구 경력 4~10년 초대졸↑ 메트로병원 기업이미지 채용시",
      "organization": "사람인",
      "category": "clinical",
      "track": "clinical",
      "region": "서울/경기",
      "employmentType": "임상병리",
      "postedAt": "",
      "deadline": "",
      "status": "unknown",
      "source": "사람인 임상병리",
      "sourceType": "job-board",
      "url": "https://m.saramin.co.kr/job-search/view?rec_idx=53656793&cn=job-industry&cns=recently-list&t_category=job_recruit&t_content=generic&referNonce=",
      "description": "임상병리사 구인 경남 창원시 의창구 경력 4~10년 초대졸↑ 메트로병원 기업이미지 채용시 스크랩 입사지원"
    },
    {
      "id": "clinical-6003342429948168101",
      "title": "의료 스크랩 급상승 척신경과 임상병리사 정규직 채용 추가모집 (신입경력무관) 대전 중구 경력무관 초대졸↑ 척신경과의원 기업이미지 ~06.14(일)",
      "organization": "사람인",
      "category": "clinical",
      "track": "clinical",
      "region": "서울/경기",
      "employmentType": "임상병리",
      "postedAt": "",
      "deadline": "",
      "status": "unknown",
      "source": "사람인 임상병리",
      "sourceType": "job-board",
      "url": "https://m.saramin.co.kr/job-search/view?rec_idx=53633454&cn=job-industry&cns=recently-list&t_category=job_recruit&t_content=generic&referNonce=",
      "description": "의료 스크랩 급상승 척신경과 임상병리사 정규직 채용 추가모집 (신입경력무관) 대전 중구 경력무관 초대졸↑ 척신경과의원 기업이미지 ~06.14(일) 스크랩 입사지원"
    },
    {
      "id": "clinical-9009791918055350810",
      "title": "수면다원검사 인천 프리랜서 임상병리사 모십니다. 인천 남동구 경력무관 초대졸↑ 빅메디칼 기업이미지 ~05.11(월)",
      "organization": "사람인",
      "category": "clinical",
      "track": "clinical",
      "region": "서울/경기",
      "employmentType": "임상병리",
      "postedAt": "",
      "deadline": "",
      "status": "unknown",
      "source": "사람인 임상병리",
      "sourceType": "job-board",
      "url": "https://m.saramin.co.kr/job-search/view?rec_idx=53600806&cn=job-industry&cns=recently-list&t_category=job_recruit&t_content=generic&referNonce=",
      "description": "수면다원검사 인천 프리랜서 임상병리사 모십니다. 인천 남동구 경력무관 초대졸↑ 빅메디칼 기업이미지 ~05.11(월) 스크랩 입사지원"
    },
    {
      "id": "clinical-2741478840872877758",
      "title": "(주5일제)(충원)경북 왜관일층정형외과에서 임상병리사 구합니다 경북 칠곡군 경력무관 학력무관 왜관일층정형외과의원 ~05.10(일)",
      "organization": "사람인",
      "category": "clinical",
      "track": "clinical",
      "region": "서울/경기",
      "employmentType": "임상병리",
      "postedAt": "",
      "deadline": "",
      "status": "unknown",
      "source": "사람인 임상병리",
      "sourceType": "job-board",
      "url": "https://m.saramin.co.kr/job-search/view?rec_idx=53590284&cn=job-industry&cns=recently-list&t_category=job_recruit&t_content=generic&referNonce=",
      "description": "(주5일제)(충원)경북 왜관일층정형외과에서 임상병리사 구합니다 경북 칠곡군 경력무관 학력무관 왜관일층정형외과의원 ~05.10(일) 스크랩 입사지원"
    },
    {
      "id": "clinical-8646871644471123604",
      "title": "의료 스크랩 급상승 [녹십자 그룹] GC셀 임상병리지원 (세종, 계약직) 세종 세종특별자치시 평균근속 2~5년 (주)지씨셀 기업이미지 채용시",
      "organization": "사람인",
      "category": "clinical",
      "track": "clinical",
      "region": "서울/경기",
      "employmentType": "임상병리",
      "postedAt": "",
      "deadline": "",
      "status": "unknown",
      "source": "사람인 임상병리",
      "sourceType": "job-board",
      "url": "https://m.saramin.co.kr/job-search/view?rec_idx=53582919&cn=job-industry&cns=recently-list&t_category=job_recruit&t_content=generic&referNonce=",
      "description": "의료 스크랩 급상승 [녹십자 그룹] GC셀 임상병리지원 (세종, 계약직) 세종 세종특별자치시 평균근속 2~5년 (주)지씨셀 기업이미지 채용시 스크랩 입사지원"
    },
    {
      "id": "clinical-9217716394100875470",
      "title": "[녹십자 그룹] GC셀 임상병리지원 (세종, 계약직, 단시간근로) 세종 세종특별자치시 평균근속 2~5년 (주)지씨셀 기업이미지 채용시",
      "organization": "사람인",
      "category": "clinical",
      "track": "clinical",
      "region": "서울/경기",
      "employmentType": "임상병리",
      "postedAt": "",
      "deadline": "",
      "status": "unknown",
      "source": "사람인 임상병리",
      "sourceType": "job-board",
      "url": "https://m.saramin.co.kr/job-search/view?rec_idx=53582903&cn=job-industry&cns=recently-list&t_category=job_recruit&t_content=generic&referNonce=",
      "description": "[녹십자 그룹] GC셀 임상병리지원 (세종, 계약직, 단시간근로) 세종 세종특별자치시 평균근속 2~5년 (주)지씨셀 기업이미지 채용시 스크랩 입사지원"
    },
    {
      "id": "clinical-3997436549114044154",
      "title": "[녹십자 그룹] GC셀 임상병리지원 (대전, 계약직) 대전 서구 성과급 연 1회 (주)지씨셀 기업이미지 채용시",
      "organization": "사람인",
      "category": "clinical",
      "track": "clinical",
      "region": "서울/경기",
      "employmentType": "임상병리",
      "postedAt": "",
      "deadline": "",
      "status": "unknown",
      "source": "사람인 임상병리",
      "sourceType": "job-board",
      "url": "https://m.saramin.co.kr/job-search/view?rec_idx=53582802&cn=job-industry&cns=recently-list&t_category=job_recruit&t_content=generic&referNonce=",
      "description": "[녹십자 그룹] GC셀 임상병리지원 (대전, 계약직) 대전 서구 성과급 연 1회 (주)지씨셀 기업이미지 채용시 스크랩 입사지원"
    },
    {
      "id": "clinical-2965980948882226958",
      "title": "[녹십자 그룹] GC셀 임상병리지원 (대전, 계약직, 단시간근로) 대전 서구 평균근속 2~5년 (주)지씨셀 기업이미지 채용시",
      "organization": "사람인",
      "category": "clinical",
      "track": "clinical",
      "region": "서울/경기",
      "employmentType": "임상병리",
      "postedAt": "",
      "deadline": "",
      "status": "unknown",
      "source": "사람인 임상병리",
      "sourceType": "job-board",
      "url": "https://m.saramin.co.kr/job-search/view?rec_idx=53582783&cn=job-industry&cns=recently-list&t_category=job_recruit&t_content=generic&referNonce=",
      "description": "[녹십자 그룹] GC셀 임상병리지원 (대전, 계약직, 단시간근로) 대전 서구 평균근속 2~5년 (주)지씨셀 기업이미지 채용시 스크랩 입사지원"
    },
    {
      "id": "clinical-5612075490441784591",
      "title": "진단검사의학과 관리, 영업부문 채용 경기 성남시 중원구 차량유류비지급 삼일약품교역(주) 기업이미지 ~05.06(수)",
      "organization": "사람인",
      "category": "clinical",
      "track": "clinical",
      "region": "경기",
      "employmentType": "임상병리",
      "postedAt": "",
      "deadline": "",
      "status": "unknown",
      "source": "사람인 임상병리",
      "sourceType": "job-board",
      "url": "https://m.saramin.co.kr/job-search/view?rec_idx=53547100&cn=job-industry&cns=recently-list&t_category=job_recruit&t_content=generic&referNonce=",
      "description": "진단검사의학과 관리, 영업부문 채용 경기 성남시 중원구 차량유류비지급 삼일약품교역(주) 기업이미지 ~05.06(수) 스크랩 입사지원"
    },
    {
      "id": "clinical-1815003486154067311",
      "title": "임상병리사 선생님 모심. (신입지원가능) 대전 중구 경력무관 초대졸↑ 보건의원 ~05.06(수)",
      "organization": "사람인",
      "category": "clinical",
      "track": "clinical",
      "region": "서울/경기",
      "employmentType": "임상병리",
      "postedAt": "",
      "deadline": "",
      "status": "unknown",
      "source": "사람인 임상병리",
      "sourceType": "job-board",
      "url": "https://m.saramin.co.kr/job-search/view?rec_idx=53544713&cn=job-industry&cns=recently-list&t_category=job_recruit&t_content=generic&referNonce=",
      "description": "임상병리사 선생님 모심. (신입지원가능) 대전 중구 경력무관 초대졸↑ 보건의원 ~05.06(수) 스크랩 입사지원"
    },
    {
      "id": "clinical-6067791242141103088",
      "title": "[녹십자 그룹] GC셀 임상병리사 모집 (의정부, 계약직) 경기 의정부시 성과급 연 1회 (주)지씨셀 기업이미지 채용시",
      "organization": "사람인",
      "category": "clinical",
      "track": "clinical",
      "region": "경기",
      "employmentType": "임상병리",
      "postedAt": "",
      "deadline": "",
      "status": "unknown",
      "source": "사람인 임상병리",
      "sourceType": "job-board",
      "url": "https://m.saramin.co.kr/job-search/view?rec_idx=53527733&cn=job-industry&cns=recently-list&t_category=job_recruit&t_content=generic&referNonce=",
      "description": "[녹십자 그룹] GC셀 임상병리사 모집 (의정부, 계약직) 경기 의정부시 성과급 연 1회 (주)지씨셀 기업이미지 채용시 스크랩 입사지원"
    },
    {
      "id": "clinical-4152706844327918520",
      "title": "[녹십자 그룹] GC셀 검체 관리 서비스 매니저 채용 (성북) 서울 강북구 자유로운 육아휴직 (주)지씨셀 기업이미지 채용시",
      "organization": "사람인",
      "category": "clinical",
      "track": "clinical",
      "region": "서울",
      "employmentType": "임상병리",
      "postedAt": "",
      "deadline": "",
      "status": "unknown",
      "source": "사람인 임상병리",
      "sourceType": "job-board",
      "url": "https://m.saramin.co.kr/job-search/view?rec_idx=53488206&cn=job-industry&cns=recently-list&t_category=job_recruit&t_content=generic&referNonce=",
      "description": "[녹십자 그룹] GC셀 검체 관리 서비스 매니저 채용 (성북) 서울 강북구 자유로운 육아휴직 (주)지씨셀 기업이미지 채용시 스크랩 입사지원"
    },
    {
      "id": "clinical-6913370909196718214",
      "title": "[녹십자 그룹] GC셀 검체 관리 서비스 매니저 채용 (청라) 인천 서구 평균근속 2~5년 (주)지씨셀 기업이미지 채용시",
      "organization": "사람인",
      "category": "clinical",
      "track": "clinical",
      "region": "서울/경기",
      "employmentType": "임상병리",
      "postedAt": "",
      "deadline": "",
      "status": "unknown",
      "source": "사람인 임상병리",
      "sourceType": "job-board",
      "url": "https://m.saramin.co.kr/job-search/view?rec_idx=53457440&cn=job-industry&cns=recently-list&t_category=job_recruit&t_content=generic&referNonce=",
      "description": "[녹십자 그룹] GC셀 검체 관리 서비스 매니저 채용 (청라) 인천 서구 평균근속 2~5년 (주)지씨셀 기업이미지 채용시 스크랩 입사지원"
    },
    {
      "id": "clinical-3560574276872853862",
      "title": "임상병리사 채용 공고 서울 금천구 식비 지원 (주)알앤엘재생의학연구소 기업이미지 채용시",
      "organization": "사람인",
      "category": "clinical",
      "track": "clinical",
      "region": "서울",
      "employmentType": "임상병리",
      "postedAt": "",
      "deadline": "",
      "status": "unknown",
      "source": "사람인 임상병리",
      "sourceType": "job-board",
      "url": "https://m.saramin.co.kr/job-search/view?rec_idx=53437589&cn=job-industry&cns=recently-list&t_category=job_recruit&t_content=generic&referNonce=",
      "description": "임상병리사 채용 공고 서울 금천구 식비 지원 (주)알앤엘재생의학연구소 기업이미지 채용시 스크랩 입사지원"
    },
    {
      "id": "clinical-3715612558171658293",
      "title": "[향남두리ENT] 임상병리사 채용합니다. 경기 화성시 상여금 향남두리이비인후과 ~05.18(월)",
      "organization": "사람인",
      "category": "clinical",
      "track": "clinical",
      "region": "경기",
      "employmentType": "임상병리",
      "postedAt": "",
      "deadline": "",
      "status": "unknown",
      "source": "사람인 임상병리",
      "sourceType": "job-board",
      "url": "https://m.saramin.co.kr/job-search/view?rec_idx=53381343&cn=job-industry&cns=recently-list&t_category=job_recruit&t_content=generic&referNonce=",
      "description": "[향남두리ENT] 임상병리사 채용합니다. 경기 화성시 상여금 향남두리이비인후과 ~05.18(월) 스크랩 입사지원"
    }
  ]
}