{
  "meta": {
    "generatedAt": "2026-07-06T23:43:53.291666",
    "source": "clinical",
    "count": 0,
    "sources": [
      "https://m.saramin.co.kr/job-industry/job-list?cat_kewd=559&is_detail_search=y",
      "https://www.seoulmc.or.kr/site/recruit/recruitList.do",
      "https://ncc.recruiter.co.kr/app/jobnotice/list",
      "https://recruit.snubh.org/main/recruit/recruit_list.do"
    ],
    "errors": [
      "https://m.saramin.co.kr/job-industry/job-list?cat_kewd=559&is_detail_search=y: HTTPSConnectionPool(host='m.saramin.co.kr', port=443): Max retries exceeded with url: /job-industry/job-list?cat_kewd=559&is_detail_search=y (Caused by ConnectTimeoutError(<HTTPSConnection(host='m.saramin.co.kr', port=443) at 0x7fe276112b70>, 'Connection to m.saramin.co.kr timed out. (connect timeout=20)'))"
    ]
  },
  "jobs": []
}